gxcv/__init__.py
gxcv/__main__.py
gxcv/main_test.py
gxcv/main_test_gxcv.py
gxcv/utils.py
gxcv/cv/__init__.py
gxcv/cv/utils.py
gxcv/cv/nn/__init__.py
gxcv/cv/nn/resnet.py
gxcv/cv/nn/unet.py
gxcv/cv/nn/unet_training.py
gxcv/cv/nn/vgg.py
gxcv-1.0.0.dist-info/LICENSE
gxcv-1.0.0.dist-info/METADATA
gxcv-1.0.0.dist-info/WHEEL
gxcv-1.0.0.dist-info/top_level.txt
gxcv-1.0.0.dist-info/RECORD
