Metadata-Version: 2.1
Name: gxcv
Version: 1.0.0
Summary: Gosion CV
Author: Gosion
Author-email: gosion@gmail.com
Classifier: Programming Language :: Python :: 3
Classifier: License :: OSI Approved :: MIT License
Classifier: Operating System :: OS Independent
Requires-Python: >=3.6
License-File: LICENSE
